nonebot_plugin_llmchat/__init__.py
nonebot_plugin_llmchat/config.py
nonebot_plugin_llmchat/mcpclient.py
nonebot_plugin_llmchat/onebottools.py
nonebot_plugin_llmchat-0.5.0.dist-info/METADATA
nonebot_plugin_llmchat-0.5.0.dist-info/WHEEL
nonebot_plugin_llmchat-0.5.0.dist-info/licenses/LICENSE
nonebot_plugin_llmchat-0.5.0.dist-info/RECORD
