Metadata-Version: 2.4
Name: nonebot-plugin-llmchat
Version: 0.5.0
Summary: Nonebot AI group chat plugin supporting multiple API preset configurations
License: GPL
License-File: LICENSE
Keywords: nonebot,nonebot2,llm,ai
Author: FuQuan i@fuquan.moe
Requires-Python: >=3.10,<4.0
Classifier: License :: Other/Proprietary License
Classifier: Programming Language :: Python :: 3
Classifier: Programming Language :: Python :: 3.10
Classifier: Programming Language :: Python :: 3.11
Classifier: Programming Language :: Python :: 3.12
Classifier: Programming Language :: Python :: 3.13
Classifier: Programming Language :: Python :: 3.14
Requires-Dist: aiofiles (>=24.0.0)
Requires-Dist: mcp (>=1.6.0,<2.0.0)
Requires-Dist: nonebot-adapter-onebot (>=2.0.0,<3.0.0)
Requires-Dist: nonebot-plugin-apscheduler (>=0.5.0,<0.6.0)
Requires-Dist: nonebot-plugin-localstore (>=0.7.3,<0.8.0)
Requires-Dist: nonebot2 (>=2.2.0,<3.0.0)
Requires-Dist: openai (>=1.0.0)
Project-URL: Documentation, https://github.com/FuQuan233/nonebot-plugin-llmchat#readme
Project-URL: Homepage, https://github.com/FuQuan233/nonebot-plugin-llmchat
Project-URL: Repository, https://github.com/FuQuan233/nonebot-plugin-llmchat
